<?xml version="1.0" encoding="utf-8" ?>
<dwsync>
<file name="ico-2.gif" server="120.24.217.136/default/" local="130633544172343750" remote="130633956000000000" Dst="0" />
<file name="picbox-listbg.gif" server="120.24.217.136/default/" local="130633544198281250" remote="130633956000000000" Dst="0" />
<file name="number-range.gif" server="120.24.217.136/default/" local="130633544193125000" remote="130633956000000000" Dst="0" />
<file name="ico-1.gif" server="120.24.217.136/default/" local="130633544169531250" remote="130633956000000000" Dst="0" />
<file name="page_bg.gif" server="120.24.217.136/default/" local="130633544195937500" remote="130633956000000000" Dst="0" />
<file name="new-article.gif" server="120.24.217.136/default/" local="130633544185156250" remote="130633956000000000" Dst="0" />
<file name="view-labeltitle-bg.gif" server="120.24.217.136/default/" local="130633544212187500" remote="130633956000000000" Dst="0" />
<file name="boxoff.gif" server="120.24.217.136/default/" local="130633544119218750" remote="130633956000000000" Dst="0" />
<file name="newdigg-bg.png" server="120.24.217.136/default/" local="130633544187968750" remote="130633956000000000" Dst="0" />
<file name="digg-bg.gif" server="120.24.217.136/default/" local="130633544161406250" remote="130633956000000000" Dst="0" />
<file name="actbox-ico.gif" server="120.24.217.136/default/" local="130633544109687500" remote="130633956000000000" Dst="0" />
<file name="downurl-bg.gif" server="120.24.217.136/default/" local="130633544164218750" remote="130633956000000000" Dst="0" />
<file name="comm-bt.gif" server="120.24.217.136/default/" local="130633544158593750" remote="130633956000000000" Dst="0" />
<file name="btn-bg2.gif" server="120.24.217.136/default/" local="130633544122187500" remote="130633956000000000" Dst="0" />
<file name="green_skin.png" server="120.24.217.136/default/" local="130633544166562500" remote="130633956000000000" Dst="0" />
<file name="search-bt.gif" server="120.24.217.136/default/" local="130633544203906250" remote="130633956000000000" Dst="0" />
<file name="channel_bg.png" server="120.24.217.136/default/" local="130633544142656250" remote="130633956000000000" Dst="0" />
<file name="white_bg.gif" server="120.24.217.136/default/" local="130633544215156250" remote="130633956000000000" Dst="0" />
<file name="search-top-bg.gif" server="120.24.217.136/default/" local="130633544206718750" remote="130633956000000000" Dst="0" />
<file name="ico-3.gif" server="120.24.217.136/default/" local="130633544177187500" remote="130633956000000000" Dst="0" />
<file name="but_bg_sr.gif" server="120.24.217.136/default/" local="130633544138125000" remote="130633956000000000" Dst="0" />
<file name="2011121720154997.jpg.middle.jpg" server="120.24.217.136/default/" local="130634277291718750" remote="130634013000000000" Dst="0" />
<file name="2011121720154997.jpg.thumb.jpg" server="120.24.217.136/default/" local="130639421804531250" remote="130639402800000000" Dst="0" />
<file name="bcastr3.swf" server="120.24.217.136/default/" local="130633544116406250" remote="130634013000000000" Dst="0" />
<file name="banner-header.png" server="120.24.217.136/default/" local="130633544112656250" remote="130634013000000000" Dst="0" />
<file name="2011121914481934.gif" server="120.24.217.136/default/" local="130639493802500000" remote="130639403400000000" Dst="0" />
<file name="bg.jpg" server="120.24.217.136/default/" local="130639441232812500" remote="130639403400000000" Dst="0" />
<file name="busbg.jpg" server="120.24.217.136/default/" local="130639441241718750" remote="130639403400000000" Dst="0" />
<file name="but_bg_sr2.gif" server="120.24.217.136/default/" local="130633544127343750" remote="130634013000000000" Dst="0" />
<file name="but_bg_sr3.gif" server="120.24.217.136/default/" local="130633544130156250" remote="130634013000000000" Dst="0" />
<file name="but_bg_sr1.gif" server="120.24.217.136/default/" local="130633544124687500" remote="130634013000000000" Dst="0" />
<file name="but_bg_sr4.gif" server="120.24.217.136/default/" local="130633544132812500" remote="130634013000000000" Dst="0" />
<file name="but_bg_sr5.gif" server="120.24.217.136/default/" local="130633544135625000" remote="130634013000000000" Dst="0" />
<file name="channel_bg_skin1.png" server="120.24.217.136/default/" local="130633544145312500" remote="130634013000000000" Dst="0" />
<file name="channel_bg_skin2.png" server="120.24.217.136/default/" local="130633544147812500" remote="130634013000000000" Dst="0" />
<file name="cmt-bad.gif" server="120.24.217.136/default/" local="130633544150468750" remote="130634013000000000" Dst="0" />
<file name="cmt-good.gif" server="120.24.217.136/default/" local="130633544153281250" remote="130634013000000000" Dst="0" />
<file name="cmt-neu.gif" server="120.24.217.136/default/" local="130633544155937500" remote="130634013000000000" Dst="0" />
<file name="cp.gif" server="120.24.217.136/default/" local="130639441238750000" remote="130639403400000000" Dst="0" />
<file name="float_bg.gif" server="120.24.217.136/default/" local="130639441245625000" remote="130639403400000000" Dst="0" />
<file name="float_s.gif" server="120.24.217.136/default/" local="130639441247031250" remote="130639403400000000" Dst="0" />
<file name="ge.gif" server="120.24.217.136/default/" local="130639441234218750" remote="130639403400000000" Dst="0" />
<file name="gsjj.gif" server="120.24.217.136/default/" local="130639441237187500" remote="130639403400000000" Dst="0" />
<file name="homepage.gif" server="120.24.217.136/default/" local="130639441243125000" remote="130639403400000000" Dst="0" />
<file name="homepage_bg.gif" server="120.24.217.136/default/" local="130639441198125000" remote="130639403400000000" Dst="0" />
<file name="ico_arrow.gif" server="120.24.217.136/default/" local="130639441236562500" remote="130639403400000000" Dst="0" />
<file name="ico_zoom.gif" server="120.24.217.136/default/" local="130639421468750000" remote="130639403400000000" Dst="0" />
<file name="img_scroll.gif" server="120.24.217.136/default/" local="130633544180156250" remote="130634013000000000" Dst="0" />
<file name="lei.gif" server="120.24.217.136/default/" local="130639441239531250" remote="130639403400000000" Dst="0" />
<file name="logo.gif" server="120.24.217.136/default/" local="130633544182812500" remote="130634013000000000" Dst="0" />
<file name="lx.gif" server="120.24.217.136/default/" local="130639441235781250" remote="130639403400000000" Dst="0" />
<file name="ly.gif" server="120.24.217.136/default/" local="130639441157968750" remote="130639403400000000" Dst="0" />
<file name="main_head.gif" server="120.24.217.136/default/" local="130639441242500000" remote="130639403400000000" Dst="0" />
<file name="menu_bg.gif" server="120.24.217.136/default/" local="130639441233437500" remote="130639403400000000" Dst="0" />
<file name="menu_on.gif" server="120.24.217.136/default/" local="130639441235000000" remote="130639403400000000" Dst="0" />
<file name="news.gif" server="120.24.217.136/default/" local="130639441237968750" remote="130639403400000000" Dst="0" />
<file name="nophoto.jpg" server="120.24.217.136/default/" local="130633544190781250" remote="130634013000000000" Dst="0" />
<file name="nopic60.gif" server="120.24.217.136/default/" local="130639421467968750" remote="130639403400000000" Dst="0" />
<file name="rsso.gif" server="120.24.217.136/default/" local="130633544201093750" remote="130634013000000000" Dst="0" />
<file name="theme.gif" server="120.24.217.136/default/" local="130633544209218750" remote="130634013000000000" Dst="0" />
<file name="webZx_bg.jpg" server="120.24.217.136/default/" local="130639441247812500" remote="130639403400000000" Dst="0" />
<file name="vip_bg.gif" server="120.24.217.136/default/" local="130639441244062500" remote="130639403400000000" Dst="0" />
<file name="2011121720181062.jpg.thumb.jpg" server="120.24.217.136/default/" local="130639421806093750" remote="130639402800000000" Dst="0" />
<file name="2011121720192560.jpg.thumb.jpg" server="120.24.217.136/default/" local="130639421806875000" remote="130639402800000000" Dst="0" />
<file name="2011121720203356.jpg.thumb.jpg" server="120.24.217.136/default/" local="130639421807656250" remote="130639402800000000" Dst="0" />
<file name="2011121720214193.jpg.thumb.jpg" server="120.24.217.136/default/" local="130639420994062500" remote="130639402800000000" Dst="0" />
<file name="2011121720233023.jpg.thumb.jpg" server="120.24.217.136/default/" local="130639420994843750" remote="130639402800000000" Dst="0" />
<file name="2011121720254963.jpg.thumb.jpg" server="120.24.217.136/default/" local="130639420995468750" remote="130639402800000000" Dst="0" />
<file name="2011121720270838.jpg.thumb.jpg" server="120.24.217.136/default/" local="130639420997343750" remote="130639402800000000" Dst="0" />
<file name="2011121720262638.jpg.thumb.jpg" server="120.24.217.136/default/" local="130639420996562500" remote="130639402800000000" Dst="0" />
<file name="2011121720303634.jpg.thumb.jpg" server="120.24.217.136/default/" local="130639420975781250" remote="130639403400000000" Dst="0" />
<file name="2011121720295245.jpg.thumb.jpg" server="120.24.217.136/default/" local="130639420998125000" remote="130639403400000000" Dst="0" />
<file name="2011121720284867.jpg.thumb.jpg" server="120.24.217.136/default/" local="130639420974218750" remote="130639403400000000" Dst="0" />
<file name="2011121720311164.jpg.middle.jpg" server="120.24.217.136/default/" local="130639421466406250" remote="130639403400000000" Dst="0" />
<file name="2011121720311164.jpg.thumb.jpg" server="120.24.217.136/default/" local="130639421467187500" remote="130639403400000000" Dst="0" />
<file name="2011121720320244.jpg.thumb.jpg" server="120.24.217.136/default/" local="130639420999687500" remote="130639403400000000" Dst="0" />
<file name="2011121720323236.jpg.thumb.jpg" server="120.24.217.136/default/" local="130639421000468750" remote="130639403400000000" Dst="0" />
<file name="2011121720330377.jpg.thumb.jpg" server="120.24.217.136/default/" local="130639421001093750" remote="130639403400000000" Dst="0" />
<file name="2011121720333555.jpg.thumb.jpg" server="120.24.217.136/default/" local="130639420976562500" remote="130639403400000000" Dst="0" />
<file name="2011121720343663.jpg.thumb.jpg" server="120.24.217.136/default/" local="130639420977968750" remote="130639403400000000" Dst="0" />
<file name="2011121720352798.jpg.thumb.jpg" server="120.24.217.136/default/" local="130639420978593750" remote="130639403400000000" Dst="0" />
<file name="2011121720373894.jpg.thumb.jpg" server="120.24.217.136/default/" local="130639420979375000" remote="130639403400000000" Dst="0" />
<file name="2011121720400276.jpg.thumb.jpg" server="120.24.217.136/default/" local="130639420981875000" remote="130639403400000000" Dst="0" />
<file name="2011121720404441.jpg.thumb.jpg" server="120.24.217.136/default/" local="130639420980312500" remote="130639403400000000" Dst="0" />
<file name="2011121720423860.jpg.thumb.jpg" server="120.24.217.136/default/" local="130639420982656250" remote="130639403400000000" Dst="0" />
<file name="2011121720431040.jpg.thumb.jpg" server="120.24.217.136/default/" local="130639420983437500" remote="130639403400000000" Dst="0" />
<file name="2011121720434024.jpg.thumb.jpg" server="120.24.217.136/default/" local="130639420981093750" remote="130639403400000000" Dst="0" />
<file name="2011121720492066.jpg.thumb.jpg" server="120.24.217.136/default/" local="130639420984062500" remote="130639403400000000" Dst="0" />
<file name="2011121720500856.jpg.thumb.jpg" server="120.24.217.136/default/" local="130639420984843750" remote="130639403400000000" Dst="0" />
<file name="2011121720573468.jpg.thumb.jpg" server="120.24.217.136/default/" local="130639420986406250" remote="130639403400000000" Dst="0" />
<file name="2011121720593024.jpg.thumb.jpg" server="120.24.217.136/default/" local="130639420987031250" remote="130639403400000000" Dst="0" />
<file name="2011121720594437.jpg.thumb.jpg" server="120.24.217.136/default/" local="130639420987812500" remote="130639403400000000" Dst="0" />
<file name="2011121721000399.jpg.thumb.jpg" server="120.24.217.136/default/" local="130639421001875000" remote="130639403400000000" Dst="0" />
<file name="2011121721002425.jpg.thumb.jpg" server="120.24.217.136/default/" local="130639420988593750" remote="130639403400000000" Dst="0" />
<file name="2011121721004596.jpg.thumb.jpg" server="120.24.217.136/default/" local="130639420989375000" remote="130639403400000000" Dst="0" />
<file name="2011121721020489.jpg.thumb.jpg" server="120.24.217.136/default/" local="130639421002656250" remote="130639403400000000" Dst="0" />
<file name="2011121721025893.jpg.thumb.jpg" server="120.24.217.136/default/" local="130639421003437500" remote="130639403400000000" Dst="0" />
<file name="2011121721032072.jpg.thumb.jpg" server="120.24.217.136/default/" local="130639421004218750" remote="130639403400000000" Dst="0" />
<file name="2011121721042116.jpg.thumb.jpg" server="120.24.217.136/default/" local="130639420990156250" remote="130639403400000000" Dst="0" />
<file name="2011121721044073.jpg.thumb.jpg" server="120.24.217.136/default/" local="130639421005000000" remote="130639403400000000" Dst="0" />
<file name="2011121721045498.jpg.thumb.jpg" server="120.24.217.136/default/" local="130639421005625000" remote="130639403400000000" Dst="0" />
<file name="2011121722215373.png" server="120.24.217.136/default/" local="130639440084843750" remote="130639403400000000" Dst="0" />
<file name="2011121914481934.psd" server="120.24.217.136/default/" local="130639493908593750" remote="130639403400000000" Dst="0" />
<file name="inquiry.gif" server="120.24.217.136/default/" local="130639421805312500" remote="130639403400000000" Dst="0" />
<file name="more.gif" server="120.24.217.136/default/" local="130639421010625000" remote="130639403400000000" Dst="0" />
<file name="2011121720564085.jpg.thumb.jpg" server="120.24.217.136/default/" local="130639420985625000" remote="130639403400000000" Dst="0" />
<file name="button_111.gif" server="120.24.217.136/default/" local="130640321554687500" remote="130640035800000000" Dst="0" />
</dwsync>