<?xml version="1.0" encoding="utf-8" ?>
<dwsync>
<file name="ico-mood-1.gif" server="120.24.217.136/default/" local="130633544021718750" remote="130634013000000000" Dst="0" />
<file name="ico-mood-10.gif" server="120.24.217.136/default/" local="130633544047968750" remote="130634013000000000" Dst="0" />
<file name="ico-mood-11.gif" server="120.24.217.136/default/" local="130633544050937500" remote="130634013000000000" Dst="0" />
<file name="ico-mood-12.gif" server="120.24.217.136/default/" local="130633544053437500" remote="130634013000000000" Dst="0" />
<file name="ico-mood-2.gif" server="120.24.217.136/default/" local="130633544024531250" remote="130634013000000000" Dst="0" />
<file name="ico-mood-3.gif" server="120.24.217.136/default/" local="130633544027812500" remote="130634013000000000" Dst="0" />
<file name="ico-mood-4.gif" server="120.24.217.136/default/" local="130633544030781250" remote="130634013000000000" Dst="0" />
<file name="ico-mood-5.gif" server="120.24.217.136/default/" local="130633544033593750" remote="130634013000000000" Dst="0" />
<file name="ico-mood-6.gif" server="120.24.217.136/default/" local="130633544036250000" remote="130634013000000000" Dst="0" />
<file name="ico-mood-7.gif" server="120.24.217.136/default/" local="130633544039375000" remote="130634013000000000" Dst="0" />
<file name="ico-mood-8.gif" server="120.24.217.136/default/" local="130633544042187500" remote="130634013000000000" Dst="0" />
<file name="ico-mood-9.gif" server="120.24.217.136/default/" local="130633544045312500" remote="130634013000000000" Dst="0" />
</dwsync>